setup.py
EasyLEED.egg-info/PKG-INFO
EasyLEED.egg-info/SOURCES.txt
EasyLEED.egg-info/dependency_links.txt
EasyLEED.egg-info/entry_points.txt
EasyLEED.egg-info/requires.txt
EasyLEED.egg-info/top_level.txt
easyleed/__init__.py
easyleed/__main__.py
easyleed/base.py
easyleed/defaultconfig.py
easyleed/gui.py
easyleed/io.py
easyleed/kalman.py
easyleed/qt.py
easyleed/test.py