Metadata-Version: 1.1
Name: EasyLEED
Version: 2.5.2
Summary: Automated extraction of intensity-energy spectra from low-energy electron diffraction patterns
Home-page: https://andim.github.io/easyleed/
Author: Andreas Mayer, Hanna Salopaasi, Nicola Ferralis
Author-email: andimscience@gmail.com
License: GPLv2
Download-URL: https://github.com/andim/easyleed/archive/2.5.2.tar.gz
Keywords: LEED,surface science,image analysis,I(E) spectra,spot tracking
Platform: any
Classifier: License :: OSI Approved :: GNU General Public License v2 (GPLv2)
Classifier: Development Status :: 5 - Production/Stable
Classifier: Programming Language :: Python
Classifier: Programming Language :: Python :: 2
Classifier: Programming Language :: Python :: 2.7
Classifier: Programming Language :: Python :: 3
Classifier: Programming Language :: Python :: 3.5
Classifier: Programming Language :: Python :: 3.6
Classifier: Intended Audience :: Science/Research
Classifier: Topic :: Scientific/Engineering :: Chemistry
Classifier: Topic :: Scientific/Engineering :: Physics
